{
    "shoulder_pan": {
        "id": 1,
        "drive_mode": 0,
        "homing_offset": -1356,
        "range_min": 1140,
        "range_max": 3030
    },
    "shoulder_lift": {
        "id": 2,
        "drive_mode": 0,
        "homing_offset": -1629,
        "range_min": 849,
        "range_max": 3238
    },
    "elbow_flex": {
        "id": 3,
        "drive_mode": 0,
        "homing_offset": 1684,
        "range_min": 790,
        "range_max": 3010
    },
    "wrist_flex": {
        "id": 4,
        "drive_mode": 0,
        "homing_offset": -1525,
        "range_min": 919,
        "range_max": 3297
    },
    "wrist_roll": {
        "id": 5,
        "drive_mode": 0,
        "homing_offset": 1653,
        "range_min": 186,
        "range_max": 4012
    },
    "gripper": {
        "id": 6,
        "drive_mode": 0,
        "homing_offset": -1998,
        "range_min": 1997,
        "range_max": 3511
    }
}